README.rst
setup.py
django_homebanking.egg-info/PKG-INFO
django_homebanking.egg-info/SOURCES.txt
django_homebanking.egg-info/dependency_links.txt
django_homebanking.egg-info/requires.txt
django_homebanking.egg-info/top_level.txt
homebanking/__init__.py
homebanking/admin.py
homebanking/models.py
homebanking/tests.py
homebanking/testsettings.py
homebanking/urls.py
homebanking/utils.py
homebanking/views.py
homebanking/drivers/__init__.py
homebanking/drivers/sparnord.py
homebanking/management/__init__.py
homebanking/management/commands/__init__.py
homebanking/management/commands/create_accounts.py
homebanking/management/commands/create_agreements.py
homebanking/management/commands/update_accounts.py
homebanking/migrations/0001_initial.py
homebanking/migrations/0002_auto__chg_field_account_accountnr.py
homebanking/migrations/__init__.py
homebanking/templatetags/__init__.py
homebanking/templatetags/currency.py