Metadata-Version: 1.0
Name: django-homebanking
Version: 0.2
Summary: Django appp to analyse and present data from homebanking system
Home-page: http://github.com/sorenh/python-django-homebanking
Author: Soren Hansen
Author-email: soren@linux2go.dk
License: Apache 2.0
Keywords: homebanking
Platform: UNKNOWN
